_anntoolkit.cp38-win_amd64.pyd
anntoolkit/__init__.py
anntoolkit/app.py
anntoolkit/downsample2x.py
anntoolkit/generate_mipmaps.py
anntoolkit-0.0.6.dist-info/METADATA
anntoolkit-0.0.6.dist-info/WHEEL
anntoolkit-0.0.6.dist-info/top_level.txt
anntoolkit-0.0.6.dist-info/RECORD
