Metadata-Version: 2.1
Name: anntoolkit
Version: 0.0.6
Summary: anntoolkit
Home-page: https://github.com/podgorskiy/anntoolkit
Author: Stanislav Pidhorskyi
Author-email: stpidhorskyi@mix.wvu.edu
License: MIT
